README.md
setup.cfg
setup.py
Mcko/__init__.py
Mcko/main.py
SdamGIA_PY.egg-info/PKG-INFO
SdamGIA_PY.egg-info/SOURCES.txt
SdamGIA_PY.egg-info/dependency_links.txt
SdamGIA_PY.egg-info/top_level.txt