Metadata-Version: 2.4
Name: SdamGIA_PY
Version: 0.0.1
Summary: A Python module for preparation for mcco
Author: Fedor Tyulpin
Author-email: f.tyulpin@gmail.com
Keywords: converting numbers numeral systems
Classifier: Programming Language :: Python :: 3.13
Classifier: Operating System :: OS Independent
Requires-Python: >=3.6
Dynamic: author
Dynamic: author-email
Dynamic: classifier
Dynamic: description
Dynamic: description-content-type
Dynamic: keywords
Dynamic: requires-python
Dynamic: summary
